neurotk/__init__.py
neurotk/cli.py
neurotk/io.py
neurotk/preprocess.py
neurotk/report.py
neurotk/report_html.py
neurotk/report_text.py
neurotk/transforms.py
neurotk/utils.py
neurotk/validate.py
neurotk-0.3.0.dist-info/licenses/LICENSE
neurotk-0.3.0.dist-info/METADATA
neurotk-0.3.0.dist-info/WHEEL
neurotk-0.3.0.dist-info/entry_points.txt
neurotk-0.3.0.dist-info/top_level.txt
neurotk-0.3.0.dist-info/RECORD
