Metadata-Version: 2.4
Name: neurotk
Version: 0.3.0
Summary: Dataset validation and preprocessing toolkit for neurology brain imaging (NIfTI)
Author-email: Sakshi Rathi <rathi036@umn.edu>
License:                                  Apache License
Requires-Python: >=3.8
License-File: LICENSE
Requires-Dist: numpy
Requires-Dist: nibabel
Requires-Dist: scipy
Requires-Dist: matplotlib
Requires-Dist: pyyaml
Requires-Dist: fastapi
Requires-Dist: uvicorn
Requires-Dist: jinja2
Dynamic: license-file
